heppy/__init__.py
heppy/heatmap.py
heppy/histogram.py
heppy/panel.py
heppy/plot.py
heppy/readroot.py
heppy/readroot_legacy.py
heppy/readtrex.py
heppy/readyoda.py
heppy/scanroot.py
heppy/uncertainty.py
heppy/value.py
heppy/writeroot_helpers.py
heppy/yodarun.py
heppyness-2.2.1.dist-info/LICENSE
heppyness-2.2.1.dist-info/METADATA
heppyness-2.2.1.dist-info/WHEEL
heppyness-2.2.1.dist-info/top_level.txt
heppyness-2.2.1.dist-info/RECORD
