Metadata-Version: 2.1
Name: heppyness
Version: 2.2.1
Home-page: https://gitlab.cern.ch/strichte/heppy
Author: Stefan Richter
Author-email: stefan.richter@cern.ch
Maintainer: Stefan Richter
Maintainer-email: stefan.richter@cern.ch
License: HEP license, based on MIT license
Classifier: Programming Language :: Python :: 3
Classifier: License :: OSI Approved :: MIT License
Classifier: Operating System :: OS Independent
Classifier: Intended Audience :: Science/Research
Classifier: Intended Audience :: Developers
Classifier: Topic :: Scientific/Engineering :: Physics
Requires-Python: >=3.6
License-File: LICENSE
Requires-Dist: matplotlib
Requires-Dist: numpy
Requires-Dist: uproot
Requires-Dist: uproot-methods
Requires-Dist: awkward
Requires-Dist: pandas
Requires-Dist: pyyaml
Requires-Dist: sphinx-rtd-theme
